[
    {
        "id": "1.1",
        "sifra": "polnaOpeka1800",
        "opis": "Polna opeka",
        "lambda": 0.76,
        "gostota": 1800,
        "specificnaToplota": 920,
        "difuzijskaUpornost": 12
    },
    {
        "id": "1.2",
        "sifra": "polnaOpeka",
        "opis": "Polna opeka",
        "lambda": 0.64,
        "gostota": 1600,
        "specificnaToplota": 920,
        "difuzijskaUpornost": 9
    },
    {
        "id": "1.3",
        "sifra": "polnaOpeka1400",
        "opis": "Polna opeka",
        "lambda": 0.58,
        "gostota": 1600,
        "specificnaToplota": 920,
        "difuzijskaUpornost": 7
    },
    {
        "id": "1.4",
        "sifra": "polnaOpeka1200",
        "opis": "Polna opeka",
        "lambda": 0.47,
        "gostota": 1200,
        "specificnaToplota": 920,
        "difuzijskaUpornost": 5
    },
    {
        "id": "2.1",
        "sifra": "opeka",
        "opis": "Mrežasta in votla opeka",
        "lambda": 0.61,
        "gostota": 1400,
        "specificnaToplota": 920,
        "difuzijskaUpornost": 6
    },
    {
        "id": "2.2",
        "sifra": "opeka1200",
        "opis": "Mrežasta in votla opeka",
        "lambda": 0.52,
        "gostota": 1200,
        "specificnaToplota": 920,
        "difuzijskaUpornost": 4
    },
    {
        "id": "2.3",
        "sifra": "termoOpeka",
        "opis": "Mrežasta in votla opeka",
        "lambda": 0.23,
        "gostota": 1400,
        "specificnaToplota": 920,
        "difuzijskaUpornost": 6
    },
    {
        "id": "10.2",
        "sifra": "porobeton",
        "opis": "Betonski votlaki z odprtinami v treh vrstah",
        "lambda": 0.16,
        "gostota": 500,
        "specificnaToplota": 860,
        "difuzijskaUpornost": 5
    },
    {
        "id": "16",
        "sifra": "betonskiVotlak",
        "opis": "Betonski votlaki z odprtinami v treh vrstah",
        "lambda": 0.74,
        "gostota": 1600,
        "specificnaToplota": 960,
        "difuzijskaUpornost": 10
    },
    {
        "id": "19.1",
        "sifra": "apnenaMalta",
        "opis": "Apnena malta",
        "lambda": 0.81,
        "gostota": 1600,
        "specificnaToplota": 1050,
        "difuzijskaUpornost": 10
    },
    {
        "id": "21",
        "sifra": "cementnoLepilo",
        "opis": "Cementna malta",
        "lambda": 1.4,
        "gostota": 2100,
        "specificnaToplota": 1050,
        "difuzijskaUpornost": 30
    },
    {
        "id": "22",
        "sifra": "estrih",
        "opis": "Cementni estrih",
        "lambda": 1.4,
        "gostota": 2200,
        "specificnaToplota": 1050,
        "difuzijskaUpornost": 30
    },
    {
        "id": "23",
        "sifra": "fasadniSloj",
        "opis": "Pigmentna fasadna malta",
        "lambda": 0.7,
        "gostota": 1850,
        "specificnaToplota": 1050,
        "difuzijskaUpornost": 15
    },
    {
        "id": "25",
        "sifra": "omet",
        "opis": "Mavčna in apneno mavčna malta",
        "lambda": 0.7,
        "gostota": 1050,
        "specificnaToplota": 920,
        "difuzijskaUpornost": 9
    },
    {
        "id": "29",
        "sifra": "maltaNaTrstiki",
        "opis": "Mavčna malta na trstiki",
        "lambda": 0.47,
        "gostota": 1000,
        "specificnaToplota": 920,
        "difuzijskaUpornost": 3
    },
    {
        "id": "30",
        "sifra": "maltaNaRabicMrezi",
        "opis": "Mavčna malta na rabic mreži",
        "lambda": 0.58,
        "gostota": 1200,
        "specificnaToplota": 920,
        "difuzijskaUpornost": 4
    },
    {
        "id": "31",
        "sifra": "granit",
        "opis": "Granit, gnajs",
        "lambda": 3.5,
        "gostota": 2800,
        "specificnaToplota": 920,
        "difuzijskaUpornost": 65
    },
    {
        "id": "32",
        "sifra": "kamen",
        "opis": "Gosti apnenec, dolomit, marmor",
        "lambda": 2.3,
        "gostota": 2600,
        "specificnaToplota": 920,
        "difuzijskaUpornost": 65
    },
    {
        "id": "33",
        "sifra": "apnenec",
        "opis": "Peščenec, amorfni apnenec",
        "lambda": 1.7,
        "gostota": 2600,
        "specificnaToplota": 920,
        "difuzijskaUpornost": 50
    },
    {
        "id": "34.1",
        "sifra": "gramoz2000",
        "opis": "Pesek in drobni gramoz",
        "lambda": 1.7,
        "gostota": 2000,
        "specificnaToplota": 840,
        "difuzijskaUpornost": 15
    },
    {
        "id": "34.2",
        "sifra": "drobniGramoz",
        "opis": "Pesek in drobni gramoz",
        "lambda": 1.2,
        "gostota": 1500,
        "specificnaToplota": 840,
        "difuzijskaUpornost": 15
    },
    {
        "id": "35.1",
        "sifra": "humus2000",
        "opis": "Zaraščeno zemljišče, humus",
        "lambda": 2.6,
        "gostota": 2000,
        "specificnaToplota": 840,
        "difuzijskaUpornost": 50
    },
    {
        "id": "35.2",
        "sifra": "humus",
        "opis": "Zaraščeno zemljišče, humus",
        "lambda": 1.5,
        "gostota": 1500,
        "specificnaToplota": 840,
        "difuzijskaUpornost": 50
    },
    {
        "id": "36",
        "sifra": "pesek",
        "opis": "Pesek, suh",
        "lambda": 0.58,
        "gostota": 1800,
        "specificnaToplota": 840,
        "difuzijskaUpornost": 1.4
    },
    {
        "id": "37",
        "sifra": "tampon",
        "opis": "Gramoz, suh",
        "lambda": 0.81,
        "gostota": 1700,
        "specificnaToplota": 840,
        "difuzijskaUpornost": 1.5
    },
    {
        "id": "38",
        "sifra": "zdrobljenaOpeka",
        "opis": "Zdrobljena opeka",
        "lambda": 0.41,
        "gostota": 800,
        "specificnaToplota": 840,
        "difuzijskaUpornost": 1.3
    },
    {
        "id": "39",
        "sifra": "zdrobljenaPluta",
        "opis": "Zdrobljena pluta",
        "lambda": 0.04,
        "gostota": 50,
        "specificnaToplota": 840,
        "difuzijskaUpornost": 1.1
    },
    {
        "id": "40",
        "sifra": "nasutPerlit",
        "opis": "Perlit, nasut",
        "lambda": 0.05,
        "gostota": 100,
        "specificnaToplota": 840,
        "difuzijskaUpornost": 1.3
    },
    {
        "id": "41",
        "sifra": "nasutKeramzit",
        "opis": "Keramzit, nasut",
        "lambda": 0.22,
        "gostota": 400,
        "specificnaToplota": 840,
        "difuzijskaUpornost": 1.3
    },
    {
        "id": "42",
        "sifra": "oblanci",
        "opis": "Keramzit, nasut",
        "lambda": 0.09,
        "gostota": 250,
        "specificnaToplota": 2090,
        "difuzijskaUpornost": 1.2
    },
    {
        "id": "43",
        "sifra": "zemlja",
        "opis": "Nasuta zemlja (vlažna)",
        "lambda": 2.1,
        "gostota": 1700,
        "specificnaToplota": 840,
        "difuzijskaUpornost": 2.1
    },
    {
        "id": "44.1",
        "sifra": "beton2500",
        "opis": "Beton s kamnitimi agregati",
        "lambda": 2.33,
        "gostota": 2500,
        "specificnaToplota": 960,
        "difuzijskaUpornost": 90
    },
    {
        "id": "44.2",
        "sifra": "beton",
        "opis": "Beton s kamnitimi agregati",
        "lambda": 2.04,
        "gostota": 2400,
        "specificnaToplota": 960,
        "difuzijskaUpornost": 60
    },
    {
        "id": "44.3",
        "sifra": "beton2200",
        "opis": "Beton s kamnitimi agregati",
        "lambda": 1.51,
        "gostota": 2200,
        "specificnaToplota": 960,
        "difuzijskaUpornost": 30
    },
    {
        "id": "44.4",
        "sifra": "beton2000",
        "opis": "Beton s kamnitimi agregati",
        "lambda": 1.16,
        "gostota": 2000,
        "specificnaToplota": 960,
        "difuzijskaUpornost": 22
    },
    {
        "id": "44.5",
        "sifra": "beton1800",
        "opis": "Beton s kamnitimi agregati",
        "lambda": 0.93,
        "gostota": 1800,
        "specificnaToplota": 960,
        "difuzijskaUpornost": 15
    },
    {
        "id": "50.1",
        "sifra": "MKplosce",
        "opis": "Mavčno-kartonske plošče do 15mm",
        "lambda": 0.21,
        "gostota": 900,
        "specificnaToplota": 840,
        "difuzijskaUpornost": 12
    },
    {
        "id": "56.2",
        "sifra": "keramika",
        "opis": "Keramične ploščice, talne, neglazirane",
        "lambda": 1.28,
        "gostota": 2300,
        "specificnaToplota": 920,
        "difuzijskaUpornost": 200
    },
    {
        "id": "68.3",
        "sifra": "les",
        "opis": "Les smreka, bor",
        "lambda": 0.14,
        "gostota": 550,
        "specificnaToplota": 2090,
        "difuzijskaUpornost": 70
    },
    {
        "id": "76.1",
        "sifra": "asfalt",
        "opis": "Asfalt",
        "lambda": 0.7,
        "gostota": 2100,
        "specificnaToplota": 1050,
        "difuzijskaUpornost": 2500
    },
    {
        "id": "78",
        "sifra": "vinil",
        "opis": "PVC, homogen",
        "lambda": 0.23,
        "gostota": 1400,
        "specificnaToplota": 960,
        "difuzijskaUpornost": 10000
    },
    {
        "id": "85",
        "sifra": "PEfolija",
        "opis": "Polietilenske folije",
        "lambda": 0.19,
        "gostota": 1000,
        "specificnaToplota": 1250,
        "difuzijskaUpornost": 80000
    },
    {
        "id": "87.2",
        "sifra": "hidroizolacijaAl",
        "opis": "Bitumenski trak z vložkom Al folije debeline 0.2 mm",
        "lambda": 0.19,
        "gostota": 900,
        "specificnaToplota": 1460,
        "difuzijskaUpornost": 150000
    },
    {
        "id": "91.2",
        "sifra": "hidroizolacija",
        "opis": "Večplastna bitumenska hidroizolacija",
        "lambda": 0.19,
        "gostota": 1200,
        "specificnaToplota": 1460,
        "difuzijskaUpornost": 14000
    },
    {
        "id": "91.3",
        "sifra": "hidroizolacija2",
        "opis": "Večplastna bitumenska hidroizolacija",
        "lambda": 0.19,
        "gostota": 1100,
        "specificnaToplota": 1460,
        "difuzijskaUpornost": 2000
    },
    {
        "id": "91.4",
        "sifra": "cementnaHidroizolacija",
        "opis": "Večplastna bitumenska hidroizolacija",
        "lambda": 1.7,
        "gostota": 1700,
        "specificnaToplota": 1500,
        "difuzijskaUpornost": 1800
    },
    {
        "id": "92",
        "sifra": "PVCtrakovi",
        "opis": "PVC strešni trakovi, mehki",
        "lambda": 0.19,
        "gostota": 1200,
        "specificnaToplota": 960,
        "difuzijskaUpornost": 20000
    },
    {
        "id": "99",
        "sifra": "jeklo",
        "opis": "Jeklo, jeklena pločevina",
        "lambda": 53.5,
        "gostota": 7800,
        "specificnaToplota": 4600,
        "difuzijskaUpornost": 600000
    },
    {
        "id": "113.4",
        "sifra": "EPS100",
        "opis": "EPS 100",
        "lambda": 0.035,
        "gostota": 15,
        "specificnaToplota": 1260,
        "difuzijskaUpornost": 25
    },
    {
        "id": "113.5",
        "sifra": "stiroestrih",
        "opis": "Stiroestrih PolitermBlu 250 kg/m3",
        "lambda": 0.067,
        "gostota": 250,
        "specificnaToplota": 1260,
        "difuzijskaUpornost": 6.9
    },
    {
        "id": "114",
        "sifra": "EPSneo",
        "opis": "EPS F grafitni",
        "lambda": 0.031,
        "gostota": 15,
        "specificnaToplota": 1260,
        "difuzijskaUpornost": 25
    },
    {
        "id": "120.1",
        "sifra": "XPS",
        "opis": "Ekstrudirani polistiren (XPS)",
        "lambda": 0.035,
        "gostota": 33,
        "specificnaToplota": 1500,
        "difuzijskaUpornost": 50
    },
    {
        "id": "126.5",
        "sifra": "kamenaVolna",
        "opis": "Mineralna kamena volna",
        "lambda": 0.034,
        "gostota": 80,
        "specificnaToplota": 1030,
        "difuzijskaUpornost": 1
    },
    {
        "id": "131.3",
        "sifra": "poliuretan",
        "opis": "Poliuretanska pena",
        "lambda": 0.022,
        "gostota": 15,
        "specificnaToplota": 1500,
        "difuzijskaUpornost": 30
    },
    {
        "id": "00.1",
        "sifra": "paropropustnaFolija",
        "opis": "Paropropustna folija",
        "lambda": 0.22,
        "gostota": 250,
        "specificnaToplota": 1700,
        "difuzijskaUpornost": 40
    },
    {
        "id": "00.11",
        "sifra": "parnaOvira",
        "opis": "Parna ovira",
        "lambda": 0.22,
        "gostota": 250,
        "specificnaToplota": 1700,
        "difuzijskaUpornost": 4000
    },
    {
        "id": "00.2",
        "sifra": "parnaZapora",
        "opis": "Parna zapora",
        "lambda": 0.19,
        "gostota": 1200,
        "specificnaToplota": 960,
        "difuzijskaUpornost": 10000
    },
    {
        "id": "00.3",
        "sifra": "OSB",
        "opis": "OSB3 plošča",
        "lambda": 0.13,
        "gostota": 600,
        "specificnaToplota": 2100,
        "difuzijskaUpornost": 200
    }
]